flask_combo_jsonapi/__init__.py
flask_combo_jsonapi/api.py
flask_combo_jsonapi/decorators.py
flask_combo_jsonapi/errors.py
flask_combo_jsonapi/exceptions.py
flask_combo_jsonapi/pagination.py
flask_combo_jsonapi/plugin.py
flask_combo_jsonapi/querystring.py
flask_combo_jsonapi/resource.py
flask_combo_jsonapi/schema.py
flask_combo_jsonapi/utils.py
flask_combo_jsonapi/data_layers/__init__.py
flask_combo_jsonapi/data_layers/alchemy.py
flask_combo_jsonapi/data_layers/base.py
flask_combo_jsonapi/data_layers/shared.py
flask_combo_jsonapi/data_layers/filtering/__init__.py
flask_combo_jsonapi/data_layers/filtering/alchemy.py
flask_combo_jsonapi/data_layers/sorting/__init__.py
flask_combo_jsonapi/data_layers/sorting/alchemy.py
Flask_COMBO_JSONAPI-1.1.0.dist-info/LICENSE
Flask_COMBO_JSONAPI-1.1.0.dist-info/METADATA
Flask_COMBO_JSONAPI-1.1.0.dist-info/WHEEL
Flask_COMBO_JSONAPI-1.1.0.dist-info/top_level.txt
Flask_COMBO_JSONAPI-1.1.0.dist-info/RECORD
